sum-ex/__init__.py
sum-ex/advanced.py
sum-ex/basic.py
sumex/__init__.py
sumex/advanced.py
sumex/basic.py
sum_ex-0.1.2.dist-info/METADATA
sum_ex-0.1.2.dist-info/WHEEL
sum_ex-0.1.2.dist-info/top_level.txt
sum_ex-0.1.2.dist-info/RECORD
