Metadata-Version: 2.1
Name: sum-ex
Version: 0.1.2
Summary: A simple Python package for math operations
Home-page: https://vipstech.in
Author: Devanand
Author-email: sanjaydeva1605@gmail.com
Requires-Python: >=3.6
